__init__.py
constants.py
internet_archive_downloader.py
main.py
utils.py
wayback_date_object.py
waybackup_to_warc.py
internet_archive_extractor-0.0.10.dist-info/METADATA
internet_archive_extractor-0.0.10.dist-info/WHEEL
internet_archive_extractor-0.0.10.dist-info/entry_points.txt
internet_archive_extractor-0.0.10.dist-info/top_level.txt
internet_archive_extractor-0.0.10.dist-info/RECORD
