Metadata-Version: 2.4
Name: internet-archive-extractor
Version: 0.0.10
Summary: Tool for extracting archived web sites from the Internet Archive saving as WARC files.
Author-email: Victor Harbo Johnston <vijo@cas.au.dk>
License: MIT
Project-URL: Homepage, https://github.com/WEB-CHILD/InternetArchiveExtractor
Requires-Python: >=3.8
Requires-Dist: certifi
Requires-Dist: charset-normalizer
Requires-Dist: idna
Requires-Dist: numpy
Requires-Dist: pandas
Requires-Dist: pysqlite3
Requires-Dist: python-dateutil
Requires-Dist: python-magic
Requires-Dist: pytz
Requires-Dist: pywaybackup
Requires-Dist: requests
Requires-Dist: six
Requires-Dist: tqdm
Requires-Dist: tzdata
Requires-Dist: urllib3
Requires-Dist: warcio
